.gitignore
LICENSE
README.rst
setup.py
axado.django_localflavor_br.egg-info/PKG-INFO
axado.django_localflavor_br.egg-info/SOURCES.txt
axado.django_localflavor_br.egg-info/dependency_links.txt
axado.django_localflavor_br.egg-info/requires.txt
axado.django_localflavor_br.egg-info/top_level.txt
django_localflavor_br/__init__.py
django_localflavor_br/br_states.py
django_localflavor_br/forms.py
tests/__init__.py
tests/tests.py