Metadata-Version: 1.1
Name: axado.django-localflavor-br
Version: 1.0.1
Summary: Country-specific Django helpers for Brazil.
Home-page: https://github.com/axado/django-localflavor-br
Author: Django Software Foundation
Author-email: foundation@djangoproject.com
License: BSD
Platform: UNKNOWN
Classifier: Development Status :: 5 - Production/Stable
Classifier: Environment :: Web Environment
Classifier: Framework :: Django
Classifier: Intended Audience :: Developers
Classifier: License :: OSI Approved :: BSD License
Classifier: Operating System :: OS Independent
Classifier: Programming Language :: Python
